jupyter_echarts.py
jupyter_echarts-0.1.14.dist-info/LICENSE
jupyter_echarts-0.1.14.dist-info/WHEEL
jupyter_echarts-0.1.14.dist-info/METADATA
jupyter_echarts-0.1.14.dist-info/RECORD
